termkit/__init__.py
termkit/arguments.py
termkit/core.py
termkit/formatters.py
termkit/groups.py
termkit/parser.py
termkit/prompt.py
termkit/tests.py
termkit/utils.py
termkit-0.2.13.dist-info/LICENSE
termkit-0.2.13.dist-info/METADATA
termkit-0.2.13.dist-info/WHEEL
termkit-0.2.13.dist-info/RECORD
