Metadata-Version: 2.1
Name: termkit
Version: 0.2.13
Summary: Python command line application framework
License: MIT
Author: Thomas Mahé
Author-email: contact@tmahe.dev
Requires-Python: >=3.9,<4.0
Classifier: License :: OSI Approved :: MIT License
Classifier: Programming Language :: Python :: 3
Classifier: Programming Language :: Python :: 3.9
Classifier: Programming Language :: Python :: 3.10
Classifier: Programming Language :: Python :: 3.11
Classifier: Programming Language :: Python :: 3.12
